django_easy_timezones-0.8.0.dist-info/DESCRIPTION.rst
django_easy_timezones-0.8.0.dist-info/METADATA
django_easy_timezones-0.8.0.dist-info/RECORD
django_easy_timezones-0.8.0.dist-info/WHEEL
django_easy_timezones-0.8.0.dist-info/metadata.json
django_easy_timezones-0.8.0.dist-info/pbr.json
django_easy_timezones-0.8.0.dist-info/top_level.txt
easy_timezones/__init__.py
easy_timezones/middleware.py
easy_timezones/signals.py
easy_timezones/tests.py
easy_timezones/urls.py
easy_timezones/utils.py
easy_timezones/views.py
