Metadata-Version: 2.0
Name: django-easy-timezones
Version: 0.8.0
Summary: Easy timezones for Django (>=1.7) based on MaxMind GeoIP.
Home-page: https://github.com/Miserlou/django-easy-timezones
Author: Rich Jones
Author-email: rich@openwatch.net
License: Apache License
Platform: UNKNOWN
Classifier: Environment :: Web Environment
Classifier: Framework :: Django
Classifier: Intended Audience :: Developers
Classifier: License :: OSI Approved :: Apache Software License
Classifier: Operating System :: OS Independent
Classifier: Programming Language :: Python
Classifier: Programming Language :: Python :: 2.6
Classifier: Programming Language :: Python :: 2.7
Classifier: Programming Language :: Python :: 3.5
Classifier: Topic :: Internet :: WWW/HTTP
Classifier: Topic :: Internet :: WWW/HTTP :: Dynamic Content
Requires-Dist: Django (>=1.7)
Requires-Dist: ipaddress (==1.0.16)
Requires-Dist: pygeoip (==0.3.2)
Requires-Dist: pytz (==2016.6)
Requires-Dist: wheel (==0.29.0)
